tobytearray/__init__.py
tobytearray/converter.py
tobytearray-converter/__init__.py
tobytearray-converter/converter.py
tobytearray_converter/__init__.py
tobytearray_converter/converter.py
tobytearray-0.1.3.dist-info/LICENSE
tobytearray-0.1.3.dist-info/METADATA
tobytearray-0.1.3.dist-info/WHEEL
tobytearray-0.1.3.dist-info/entry_points.txt
tobytearray-0.1.3.dist-info/top_level.txt
tobytearray-0.1.3.dist-info/RECORD
